aswt/__init__.py
aswt/__main__.py
aswt/flask.py
aswt/require.py
aswt/starlette.py
aswt/token.py
aswt-0.0.11.dist-info/LICENSE
aswt-0.0.11.dist-info/METADATA
aswt-0.0.11.dist-info/WHEEL
aswt-0.0.11.dist-info/top_level.txt
aswt-0.0.11.dist-info/RECORD
